{
  "category_id": "100",
  "wizard": {
    "name": "CO Detector - Vision ZS6301-5",
    "countable_steps": 3,
    "delete_step": 100,
    "steps": [
      {
        "id": 1,
        "step_count": 1,
        "template": 1,
        "step_headline": {
          "lang_tag": "ui7_kitdevice_5581_headline",
          "text": "CO Detector"
        },
        "text_content": [
          {
            "static_group": 1,
            "group_type": "manual",
            "target": "",
            "group_text": {
              "lang_tag": "",
              "text": ""
            }
          },
          {
            "static_group": 2,
            "group_text": [
              {
                "lang_tag": "ui7_kitdevice_5581_step_1_11",
                "text": "Open the Battery Compartment and insert Battery as shown. (Push the button on the bottom and slide down the cover to open.)"
              },
              {
                "lang_tag": "",
                "text": ""
              }
            ]
          }
        ],
        "images": [
          {
            "static_group": 2,
            "group_image": "1024px-Device-Wizard-CO-detectors_01.jpg"
          }
        ],
        "buttons": [
          {
            "button_id": 1,
            "label": {
              "lang_tag": "ui7_devwiz_btn_exit",
              "text": "Exit"
            },
            "button_command": [
              {
                "command_type": "navigation",
                "action": {
                  "type": "action_exit_wizard",
                  "argument": 2
                }
              }
            ]
          },
          {
            "button_id": 2,
            "label": {
              "lang_tag": "ui7_devwiz_btn_next",
              "text": "Next"
            },
            "button_command": [
              {
                "command_type": "navigation",
                "action": {
                  "type": "action_go_to_step",
                  "argument": "4"
                }
              }
            ]
          }
        ]
      },
      {
        "id": 2,
        "step_count": "",
        "template": 1,
        "text_content": [
          {
            "static_group": 1,
            "group_text": [
              {
                "lang_tag": "",
                "text": ""
              }
            ]
          }
        ],
        "images": [
          {
            "static_group": 1,
            "group_image": ""
          }
        ],
        "buttons": [
          {
            "button_id": 1,
            "label": {
              "lang_tag": "ui7_devwiz_btn_exit",
              "text": "Exit"
            },
            "button_command": [
              {
                "command_type": "navigation",
                "action": {
                  "type": "action_exit_wizard",
                  "argument": 2
                }
              }
            ]
          },
          {
            "button_id": 2,
            "label": {
              "lang_tag": "ui7_devwiz_btn_next",
              "text": "Next"
            },
            "button_command": [
              {
                "command_type": "navigation",
                "action": {
                  "type": "action_go_to_step",
                  "argument": ""
                }
              }
            ]
          }
        ]
      },
      {
        "id": 3,
        "step_count": "",
        "template": 1,
        "text_content": [
          {
            "static_group": 1,
            "group_text": [
              {
                "lang_tag": "",
                "text": ""
              }
            ]
          },
          {
            "static_group": 2,
            "group_text": [
              {
                "lang_tag": "",
                "text": ""
              }
            ]
          }
        ],
        "images": [
          {
            "static_group": 1,
            "group_image": ""
          }
        ],
        "buttons": [
          {
            "button_id": 1,
            "label": {
              "lang_tag": "ui7_devwiz_btn_exit",
              "text": "Exit"
            },
            "button_command": [
              {
                "command_type": "navigation",
                "action": {
                  "type": "action_exit_wizard",
                  "argument": 2
                }
              }
            ]
          },
          {
            "button_id": 2,
            "label": {
              "lang_tag": "ui7_devwiz_btn_next",
              "text": "Next"
            },
            "button_command": [
              {
                "command_type": "navigation",
                "action": {
                  "type": "action_go_to_step",
                  "argument": 4
                }
              }
            ]
          }
        ]
      },
      {
        "id": 4,
        "step_count": 2,
        "template": 1,
        "text_content": [
          {
            "static_group": 1,
            "group_text": [
              {
                "lang_tag": "ui7_kitdevice_5581_step_4_01",
                "text": "Close the Battery Compartment. Press the Test / Mute / Program button and keep pressing for at least ONE SECOND, then release it.<br/><br/>The CO Sensor should be automatically detected within a few seconds, and a new screen will appear asking you to name it and indicate which room it is in."
              }
            ]
          },
          {
            "static_group": 2,
            "group_text": [
              {
                "lang_tag": "ui7_kitdevice_5581_step_4_11",
                "text": "If the device isn't detected in 60 seconds, click the 'Retry' button below to start the un-pairing process."
              }
            ]
          }
        ],
        "images": [
          {
            "static_group": 1,
            "group_image": "1024px-Device-Wizard-CO-detectors_02.jpg"
          }
        ],
        "auto_command": [
          {
            "command_type": "gateway",
            "action": {
              "type": "include_mode"
            }
          },
          {
            "command_type": "event",
            "event_add": "device_added",
            "action": {
              "type": "action_go_to_step",
              "argument": 5
            }
          }
        ],
        "buttons": [
          {
            "button_id": 1,
            "label": {
              "lang_tag": "ui7_devwiz_btn_exit",
              "text": "Exit"
            },
            "button_command": [
              {
                "command_type": "navigation",
                "action": {
                  "type": "action_exit_wizard",
                  "argument": 2
                }
              }
            ]
          },
          {
            "button_id": 2,
            "label": {
              "lang_tag": "ui7_devwiz_btn_reset",
              "text": "Retry"
            },
            "button_command": [
              {
                "command_type": "navigation",
                "action": {
                  "type": "action_go_to_step",
                  "argument": 6
                }
              }
            ]
          }
        ]
      },
      {
        "id": 5,
        "step_count": 4,
        "template": 3,
        "text_content": [
          {
            "static_group": 1,
            "group_text": [
              {
                "lang_tag": "ui7_install_device_name_room_step",
                "text": "Add a name for the device and assign it to a room."
              },
              {
                "lang_tag": "",
                "text": ""
              }
            ]
          }
        ],
        "images": [
          {
            "static_group": 1,
            "group_image": ""
          }
        ],
        "auto_command": [
          {
            "command_type": "event",
            "event_remove": "device_added"
          },
          {
            "command_type": "event",
            "event_remove": "device_removed"
          }
        ],
        "widgets": [
          "device_type_found"
        ],
        "buttons": [
          {
            "button_id": 1,
            "label": {
              "lang_tag": "ui7_devwiz_btn_finish",
              "text": "Finish"
            },
            "button_command": [
              {
                "command_type": "navigation",
                "action": {
                  "type": "action_exit_wizard",
                  "argument": 2
                }
              }
            ]
          }
        ]
      },
      {
        "id": 6,
        "template": 1,
        "reset_step": 1,
        "text_content": [
          {
            "static_group": 1,
            "group_text": [
              {
                "lang_tag": "ui7_devwiz_reset_intro",
                "text": "The Vera Controller will now begin the un-pairing process."
              },
              {
                "lang_tag": "ui7_kitdevice_5581_step_6_02",
                "text": "Close the Battery Compartment. Press the Test / Mute / Program button and keep pressing for at least one second.<br/><br/><b>Note</b>: The red LED settings light will flash  continuously while the CO sensor is in  'exclusion' (reset) mode."
              }
            ]
          },
          {
            "static_group": 2,
            "group_text": [
              {
                "lang_tag": "ui7_kitdevice_5581_step_6_11",
                "text": "Click the 'Try Adding It Again Button' to begin the pairing process again."
              }
            ]
          }
        ],
        "images": [
          {
            "static_group": 1,
            "group_image": "1024px-Device-Wizard-CO-detectors_02.jpg"
          }
        ],
        "auto_command": [
          {
            "command_type": "gateway",
            "action": {
              "type": "exclude_mode"
            }
          },
          {
            "command_type": "event",
            "event_remove": "device_added"
          },
          {
            "command_type": "event",
            "event_add": "device_removed",
            "action": {
              "type": "action_go_to_step",
              "argument": 1
            }
          }
        ],
        "buttons": [
          {
            "button_id": 1,
            "label": {
              "lang_tag": "ui7_devwiz_btn_exit",
              "text": "Exit"
            },
            "button_command": [
              {
                "command_type": "navigation",
                "action": {
                  "type": "action_exit_wizard",
                  "argument": 2
                }
              }
            ]
          },
          {
            "button_id": 2,
            "label": {
              "lang_tag": "ui7_devwiz_btn_add_again",
              "text": "Try adding it again"
            },
            "button_command": [
              {
                "command_type": "navigation",
                "action": {
                  "type": "action_go_to_step",
                  "argument": 1
                }
              }
            ]
          }
        ]
      },
      {
        "id": 100,
        "template": 1,
        "text_content": [
          {
            "static_group": 1,
            "group_text": [
              {
                "lang_tag": "ui7_devwiz_reset_intro",
                "text": "The Vera Controller will now begin the un-pairing process."
              },
              {
                "lang_tag": "ui7_kitdevice_5581_step_6_02",
                "text": "Close the Battery Compartment. Press the Test / Mute / Program button and keep pressing for at least one second.<br/><br/><b>Note</b>: The red LED settings light will flash  continuously while the CO sensor is in  'exclusion' (reset) mode."
              }
            ]
          }
        ],
        "images": [
          {
            "static_group": 1,
            "group_image": "1024px-Device-Wizard-CO-detectors_02.jpg"
          }
        ],
        "auto_command": [
          {
            "command_type": "gateway",
            "action": {
              "type": "exclude_mode"
            }
          },
          {
            "command_type": "event",
            "event_add": "device_removed",
            "action": {
              "type": "action_exit_wizard",
              "argument": 3
            }
          }
        ],
        "buttons": [
          {
            "button_id": 1,
            "label": {
              "lang_tag": "ui7_devwiz_btn_exit",
              "text": "Exit"
            },
            "button_command": [
              {
                "command_type": "navigation",
                "action": {
                  "type": "action_exit_wizard",
                  "argument": 2
                }
              }
            ]
          }
        ]
      }
    ]
  }
}
